{
  "updatedAt": "2026-07-06T02:30:45.239Z",
  "results": {
    "W-003": {
      "status": "passed",
      "date": "2026-07-04",
      "env": "testnet",
      "browser": "chrome",
      "runUrl": "https://github.com/gravity-technologies/qa-automation/actions/runs/28697318956"
    },
    "W-004": {
      "status": "passed",
      "date": "2026-07-04",
      "env": "testnet",
      "browser": "chrome",
      "runUrl": "https://github.com/gravity-technologies/qa-automation/actions/runs/28697898961"
    },
    "W-005": {
      "status": "passed",
      "date": "2026-07-04",
      "env": "testnet",
      "browser": "chrome",
      "runUrl": "https://github.com/gravity-technologies/qa-automation/actions/runs/28697318956"
    },
    "W-051": {
      "status": "passed",
      "date": "2026-07-04",
      "env": "testnet",
      "browser": "chrome",
      "runUrl": "https://github.com/gravity-technologies/qa-automation/actions/runs/28701345312"
    },
    "W-053": {
      "status": "passed",
      "date": "2026-07-04",
      "env": "testnet",
      "browser": "chrome",
      "runUrl": "https://github.com/gravity-technologies/qa-automation/actions/runs/28701345312"
    },
    "W-054": {
      "status": "passed",
      "date": "2026-07-04",
      "env": "testnet",
      "browser": "chrome",
      "runUrl": "https://github.com/gravity-technologies/qa-automation/actions/runs/28701345312"
    },
    "W-060": {
      "status": "passed",
      "date": "2026-07-04",
      "env": "testnet",
      "browser": "chrome",
      "runUrl": "https://github.com/gravity-technologies/qa-automation/actions/runs/28701345312"
    },
    "W-052": {
      "status": "failed",
      "date": "2026-07-04",
      "env": "testnet",
      "browser": "chrome",
      "runUrl": "https://github.com/gravity-technologies/qa-automation/actions/runs/28701345312"
    },
    "W-055": {
      "status": "passed",
      "date": "2026-07-04",
      "env": "testnet",
      "browser": "chrome",
      "runUrl": "https://github.com/gravity-technologies/qa-automation/actions/runs/28701345312"
    },
    "W-056": {
      "status": "passed",
      "date": "2026-07-04",
      "env": "testnet",
      "browser": "chrome",
      "runUrl": "https://github.com/gravity-technologies/qa-automation/actions/runs/28701345312"
    },
    "W-057": {
      "status": "passed",
      "date": "2026-07-04",
      "env": "testnet",
      "browser": "chrome",
      "runUrl": "https://github.com/gravity-technologies/qa-automation/actions/runs/28701345312"
    },
    "W-058": {
      "status": "passed",
      "date": "2026-07-04",
      "env": "testnet",
      "browser": "chrome",
      "runUrl": "https://github.com/gravity-technologies/qa-automation/actions/runs/28701345312"
    },
    "W-059": {
      "status": "passed",
      "date": "2026-07-04",
      "env": "testnet",
      "browser": "chrome",
      "runUrl": "https://github.com/gravity-technologies/qa-automation/actions/runs/28701345312"
    },
    "W-061": {
      "status": "passed",
      "date": "2026-07-04",
      "env": "testnet",
      "browser": "chrome",
      "runUrl": "https://github.com/gravity-technologies/qa-automation/actions/runs/28701345312"
    },
    "W-062": {
      "status": "passed",
      "date": "2026-07-04",
      "env": "testnet",
      "browser": "chrome",
      "runUrl": "https://github.com/gravity-technologies/qa-automation/actions/runs/28701345312"
    },
    "W-063": {
      "status": "passed",
      "date": "2026-07-04",
      "env": "testnet",
      "browser": "chrome",
      "runUrl": "https://github.com/gravity-technologies/qa-automation/actions/runs/28701345312"
    },
    "M-047": {
      "status": "failed",
      "date": "2026-07-06",
      "env": "testnet",
      "browser": "android",
      "runUrl": "https://github.com/gravity-technologies/qa-automation/actions/runs/28761590773"
    },
    "M-046": {
      "status": "passed",
      "date": "2026-07-06",
      "env": "testnet",
      "browser": "android",
      "runUrl": "https://github.com/gravity-technologies/qa-automation/actions/runs/28761590773"
    },
    "M-021": {
      "status": "passed",
      "date": "2026-07-06",
      "env": "testnet",
      "browser": "android",
      "runUrl": "https://github.com/gravity-technologies/qa-automation/actions/runs/28761590773"
    },
    "M-018": {
      "status": "passed",
      "date": "2026-07-06",
      "env": "testnet",
      "browser": "android",
      "runUrl": "https://github.com/gravity-technologies/qa-automation/actions/runs/28761590773"
    },
    "M-006": {
      "status": "passed",
      "date": "2026-07-06",
      "env": "testnet",
      "browser": "android",
      "runUrl": "https://github.com/gravity-technologies/qa-automation/actions/runs/28761590773"
    },
    "M-020": {
      "status": "passed",
      "date": "2026-07-06",
      "env": "testnet",
      "browser": "android",
      "runUrl": "https://github.com/gravity-technologies/qa-automation/actions/runs/28761590773"
    },
    "M-025": {
      "status": "passed",
      "date": "2026-07-06",
      "env": "testnet",
      "browser": "android",
      "runUrl": "https://github.com/gravity-technologies/qa-automation/actions/runs/28761590773"
    },
    "M-013": {
      "status": "passed",
      "date": "2026-07-06",
      "env": "testnet",
      "browser": "android",
      "runUrl": "https://github.com/gravity-technologies/qa-automation/actions/runs/28761590773"
    },
    "M-015": {
      "status": "passed",
      "date": "2026-07-06",
      "env": "testnet",
      "browser": "android",
      "runUrl": "https://github.com/gravity-technologies/qa-automation/actions/runs/28761590773"
    },
    "M-026": {
      "status": "passed",
      "date": "2026-07-06",
      "env": "testnet",
      "browser": "android",
      "runUrl": "https://github.com/gravity-technologies/qa-automation/actions/runs/28761590773"
    },
    "M-012": {
      "status": "passed",
      "date": "2026-07-06",
      "env": "testnet",
      "browser": "android",
      "runUrl": "https://github.com/gravity-technologies/qa-automation/actions/runs/28761590773"
    },
    "M-009": {
      "status": "failed",
      "date": "2026-07-06",
      "env": "testnet",
      "browser": "android",
      "runUrl": "https://github.com/gravity-technologies/qa-automation/actions/runs/28761590773"
    },
    "M-027": {
      "status": "passed",
      "date": "2026-07-06",
      "env": "testnet",
      "browser": "android",
      "runUrl": "https://github.com/gravity-technologies/qa-automation/actions/runs/28761590773"
    },
    "M-032": {
      "status": "passed",
      "date": "2026-07-06",
      "env": "testnet",
      "browser": "android",
      "runUrl": "https://github.com/gravity-technologies/qa-automation/actions/runs/28761590773"
    },
    "M-024": {
      "status": "passed",
      "date": "2026-07-06",
      "env": "testnet",
      "browser": "android",
      "runUrl": "https://github.com/gravity-technologies/qa-automation/actions/runs/28761590773"
    },
    "M-033": {
      "status": "passed",
      "date": "2026-07-06",
      "env": "testnet",
      "browser": "android",
      "runUrl": "https://github.com/gravity-technologies/qa-automation/actions/runs/28761590773"
    },
    "M-023": {
      "status": "passed",
      "date": "2026-07-06",
      "env": "testnet",
      "browser": "android",
      "runUrl": "https://github.com/gravity-technologies/qa-automation/actions/runs/28761590773"
    },
    "M-014": {
      "status": "passed",
      "date": "2026-07-06",
      "env": "testnet",
      "browser": "android",
      "runUrl": "https://github.com/gravity-technologies/qa-automation/actions/runs/28761590773"
    },
    "M-022": {
      "status": "passed",
      "date": "2026-07-06",
      "env": "testnet",
      "browser": "android",
      "runUrl": "https://github.com/gravity-technologies/qa-automation/actions/runs/28761590773"
    },
    "M-008": {
      "status": "passed",
      "date": "2026-07-06",
      "env": "testnet",
      "browser": "android",
      "runUrl": "https://github.com/gravity-technologies/qa-automation/actions/runs/28761590773"
    },
    "M-028": {
      "status": "passed",
      "date": "2026-07-06",
      "env": "testnet",
      "browser": "android",
      "runUrl": "https://github.com/gravity-technologies/qa-automation/actions/runs/28761590773"
    }
  }
}
